{"chunk_definitions":[{"row":50,"row_count":1,"visible":true,"expansion_state":0,"options":{"engine":"r","label":"unnamed-chunk-3"},"document_id":"B757FC54","chunk_id":"cl5g1p69lruuu","chunk_label":"unnamed-chunk-1"},{"row":65,"row_count":1,"visible":true,"expansion_state":0,"options":{"engine":"r","label":"unnamed-chunk-6"},"document_id":"B757FC54","chunk_id":"crstj5iqt602z","chunk_label":"unnamed-chunk-2"},{"row":79,"row_count":1,"visible":true,"expansion_state":0,"options":{"engine":"r","label":"unnamed-chunk-7"},"document_id":"B757FC54","chunk_id":"cz3ygm4e2f71h","chunk_label":"unnamed-chunk-4"},{"row":85,"row_count":1,"visible":true,"expansion_state":0,"options":{"engine":"r","label":"unnamed-chunk-8"},"document_id":"B757FC54","chunk_id":"cij5gaiftjd9u","chunk_label":"unnamed-chunk-5"},{"row":111,"row_count":1,"visible":true,"expansion_state":0,"options":{"engine":"r","label":"unnamed-chunk-9"},"document_id":"B757FC54","chunk_id":"cq5r5gcpt2a89","chunk_label":"unnamed-chunk-6"},{"row":122,"row_count":1,"visible":true,"expansion_state":0,"options":{"engine":"r","label":"unnamed-chunk-10"},"document_id":"B757FC54","chunk_id":"cw7zwbzmtbi3v","chunk_label":"unnamed-chunk-7"}],"doc_write_time":1633541596}